dm_env_rpc/__init__.py
dm_env_rpc/_version.py
dm_env_rpc/v1/__init__.py
dm_env_rpc/v1/async_connection.py
dm_env_rpc/v1/async_connection_test.py
dm_env_rpc/v1/connection.py
dm_env_rpc/v1/connection_test.py
dm_env_rpc/v1/dm_env_adaptor.py
dm_env_rpc/v1/dm_env_adaptor_test.py
dm_env_rpc/v1/dm_env_flatten_utils.py
dm_env_rpc/v1/dm_env_flatten_utils_test.py
dm_env_rpc/v1/dm_env_rpc_pb2.py
dm_env_rpc/v1/dm_env_rpc_pb2_grpc.py
dm_env_rpc/v1/dm_env_rpc_test.py
dm_env_rpc/v1/dm_env_utils.py
dm_env_rpc/v1/dm_env_utils_test.py
dm_env_rpc/v1/error.py
dm_env_rpc/v1/error_test.py
dm_env_rpc/v1/message_utils.py
dm_env_rpc/v1/message_utils_test.py
dm_env_rpc/v1/spec_manager.py
dm_env_rpc/v1/spec_manager_test.py
dm_env_rpc/v1/tensor_spec_utils.py
dm_env_rpc/v1/tensor_spec_utils_test.py
dm_env_rpc/v1/tensor_utils.py
dm_env_rpc/v1/tensor_utils_benchmark.py
dm_env_rpc/v1/tensor_utils_test.py
dm_env_rpc/v1/compliance/__init__.py
dm_env_rpc/v1/compliance/create_destroy_world.py
dm_env_rpc/v1/compliance/join_leave_world.py
dm_env_rpc/v1/compliance/reset.py
dm_env_rpc/v1/compliance/reset_world.py
dm_env_rpc/v1/compliance/step.py
dm_env_rpc/v1/extensions/__init__.py
dm_env_rpc/v1/extensions/properties.py
dm_env_rpc/v1/extensions/properties_pb2.py
dm_env_rpc/v1/extensions/properties_pb2_grpc.py
dm_env_rpc/v1/extensions/properties_test.py
dm_env_rpc-1.1.6.dist-info/LICENSE
dm_env_rpc-1.1.6.dist-info/METADATA
dm_env_rpc-1.1.6.dist-info/WHEEL
dm_env_rpc-1.1.6.dist-info/top_level.txt
dm_env_rpc-1.1.6.dist-info/RECORD
