Metadata-Version: 2.1
Name: dm-env-rpc
Version: 1.1.6
Summary: A networking protocol for agent-environment communication.
Home-page: UNKNOWN
Author: DeepMind
License: Apache License, Version 2.0
Keywords: reinforcement-learning python machine learning
Platform: UNKNOWN
Classifier: Development Status :: 5 - Production/Stable
Classifier: Environment :: Console
Classifier: Intended Audience :: Science/Research
Classifier: License :: OSI Approved :: Apache Software License
Classifier: Operating System :: POSIX :: Linux
Classifier: Operating System :: Microsoft :: Windows
Classifier: Operating System :: MacOS :: MacOS X
Classifier: Programming Language :: Python :: 3.8
Classifier: Programming Language :: Python :: 3.9
Classifier: Programming Language :: Python :: 3.10
Classifier: Programming Language :: Python :: 3.11
Classifier: Topic :: Scientific/Engineering :: Artificial Intelligence
Requires-Python: >=3.7
Requires-Dist: dm-env >=1.2
Requires-Dist: immutabledict
Requires-Dist: googleapis-common-protos
Requires-Dist: grpcio
Requires-Dist: numpy
Requires-Dist: protobuf >=3.8
Provides-Extra: examples
Requires-Dist: pygame ; extra == 'examples'
